{"metadata": {"dbt_schema_version": "https://schemas.getdbt.com/dbt/run-results/v6.json", "dbt_version": "1.8.7", "generated_at": "2025-05-18T13:30:18.801096Z", "invocation_id": "1ed42d7a-8150-4980-b95e-1d05f28b09cf", "env": {}}, "results": [], "elapsed_time": 0.0, "args": {"log_format": "default", "partial_parse": true, "require_explicit_package_overrides_for_builtin_materializations": true, "version_check": true, "send_anonymous_usage_stats": true, "use_colors_file": true, "log_file_max_bytes": 10485760, "log_level_file": "debug", "printer_width": 80, "defer": false, "introspect": true, "macro_debugging": false, "quiet": false, "project_dir": "/opt/airflow/dbt", "write_json": true, "log_path": "/opt/airflow/dbt/logs", "indirect_selection": "eager", "vars": {}, "which": "test", "print": true, "select": [], "populate_cache": true, "show_resource_report": false, "target": "dev", "require_resource_names_without_spaces": false, "log_level": "info", "enable_legacy_logger": false, "cache_selected_only": false, "strict_mode": false, "log_format_file": "debug", "exclude": [], "favor_state": false, "use_colors": true, "source_freshness_run_project_hooks": false, "profiles_dir": "/opt/airflow/dbt", "invocation_command": "dbt test", "warn_error_options": {"include": [], "exclude": []}, "static_parser": true, "partial_parse_file_diff": true}}